xsdata_odoo/__init__.py
xsdata_odoo/filters.py
xsdata_odoo/generator.py
xsdata_odoo/hook.py
xsdata_odoo/text_utils.py
xsdata_odoo/templates/class.jinja2
xsdata_odoo/templates/enum.jinja2
xsdata_odoo/templates/imports.jinja2
xsdata_odoo/templates/module.jinja2
xsdata_odoo/templates/package.jinja2
xsdata_odoo-1.0.0.dist-info/licenses/LICENSE
xsdata_odoo-1.0.0.dist-info/METADATA
xsdata_odoo-1.0.0.dist-info/WHEEL
xsdata_odoo-1.0.0.dist-info/entry_points.txt
xsdata_odoo-1.0.0.dist-info/top_level.txt
xsdata_odoo-1.0.0.dist-info/RECORD
